idle.py
idle-1.0.3.dist-info/LICENSE
idle-1.0.3.dist-info/METADATA
idle-1.0.3.dist-info/WHEEL
idle-1.0.3.dist-info/top_level.txt
idle-1.0.3.dist-info/RECORD
