Metadata-Version: 2.1
Name: idle
Version: 1.0.3
Summary: Alternavtive of notepad
Home-page: UNKNOWN
Author: Devesh Sharma
License: UNKNOWN
Platform: UNKNOWN
Classifier: Programming Language :: Python :: 3
Classifier: License :: OSI Approved :: MIT License
Classifier: Operating System :: OS Independent
Requires-Python: >=3.6
License-File: LICENSE
